{
  "openapi": "3.0.0",
  "paths": {
    "/api": {
      "get": {
        "operationId": "AppController_getData",
        "parameters": [],
        "responses": {
          "200": {
            "description": ""
          }
        }
      }
    },
    "/api/cognito-testing-login": {
      "post": {
        "operationId": "CognitoTestingController_login",
        "parameters": [],
        "responses": {
          "201": {
            "description": ""
          }
        }
      }
    },
    "/api/media-items/visibilities": {
      "get": {
        "operationId": "MediaItemController_getVisibilities",
        "parameters": [],
        "responses": {
          "200": {
            "description": ""
          }
        },
        "tags": ["media-items"]
      }
    },
    "/api/media-items": {
      "post": {
        "operationId": "MediaItemController_create",
        "parameters": [],
        "requestBody": {
          "required": true,
          "content": {
            "application/json": {
              "schema": {
                "$ref": "#/components/schemas/CreateMediaItemDto"
              }
            }
          }
        },
        "responses": {
          "201": {
            "description": "",
            "content": {
              "application/json": {
                "schema": {
                  "$ref": "#/components/schemas/MediaItem"
                }
              }
            }
          }
        },
        "tags": ["media-items"],
        "security": [
          {
            "bearer": []
          }
        ]
      },
      "get": {
        "operationId": "MediaItemController_findAll",
        "parameters": [
          {
            "name": "text",
            "required": false,
            "in": "query",
            "allowEmptyValue": true,
            "schema": {
              "type": "string"
            }
          },
          {
            "name": "tags",
            "required": false,
            "in": "query",
            "explode": true,
            "allowEmptyValue": true,
            "schema": {
              "type": "array",
              "items": {
                "type": "string"
              }
            }
          }
        ],
        "responses": {
          "200": {
            "description": "",
            "content": {
              "application/json": {
                "schema": {
                  "type": "array",
                  "items": {
                    "$ref": "#/components/schemas/MediaItemDto"
                  }
                }
              }
            }
          }
        },
        "tags": ["media-items"],
        "security": [
          {
            "bearer": []
          }
        ]
      }
    },
    "/api/media-items/{mediaId}": {
      "put": {
        "operationId": "MediaItemController_update",
        "parameters": [
          {
            "name": "mediaId",
            "required": true,
            "in": "path",
            "schema": {
              "type": "string"
            }
          }
        ],
        "requestBody": {
          "required": true,
          "content": {
            "application/json": {
              "schema": {
                "$ref": "#/components/schemas/UpdateMediaItemDto"
              }
            }
          }
        },
        "responses": {
          "200": {
            "description": "",
            "content": {
              "application/json": {
                "schema": {
                  "$ref": "#/components/schemas/MediaItem"
                }
              }
            }
          }
        },
        "tags": ["media-items"],
        "security": [
          {
            "bearer": []
          }
        ]
      },
      "delete": {
        "operationId": "MediaItemController_remove",
        "parameters": [
          {
            "name": "mediaId",
            "required": true,
            "in": "path",
            "schema": {
              "type": "string"
            }
          }
        ],
        "responses": {
          "200": {
            "description": ""
          }
        },
        "tags": ["media-items"],
        "security": [
          {
            "bearer": []
          }
        ]
      },
      "get": {
        "operationId": "MediaItemController_findOne",
        "parameters": [
          {
            "name": "mediaId",
            "required": true,
            "in": "path",
            "schema": {
              "type": "string"
            }
          }
        ],
        "responses": {
          "200": {
            "description": "",
            "content": {
              "application/json": {
                "schema": {
                  "$ref": "#/components/schemas/MediaItemDto"
                }
              }
            }
          }
        },
        "tags": ["media-items"],
        "security": [
          {
            "bearer": []
          }
        ]
      }
    },
    "/api/media-items/{mediaId}/share/{userId}": {
      "post": {
        "operationId": "MediaItemController_share",
        "parameters": [
          {
            "name": "mediaId",
            "required": true,
            "in": "path",
            "schema": {
              "type": "string"
            }
          },
          {
            "name": "userId",
            "required": true,
            "in": "path",
            "schema": {
              "type": "string"
            }
          },
          {
            "name": ":userId",
            "required": true,
            "in": "path",
            "schema": {
              "type": "string"
            }
          }
        ],
        "responses": {
          "201": {
            "description": "",
            "content": {
              "application/json": {
                "schema": {
                  "$ref": "#/components/schemas/ShareItem"
                }
              }
            }
          }
        },
        "tags": ["media-items"],
        "security": [
          {
            "bearer": []
          }
        ]
      }
    },
    "/api/media-items/popular": {
      "get": {
        "operationId": "MediaItemController_findPopular",
        "parameters": [],
        "responses": {
          "200": {
            "description": "",
            "content": {
              "application/json": {
                "schema": {
                  "type": "array",
                  "items": {
                    "$ref": "#/components/schemas/MediaItemDto"
                  }
                }
              }
            }
          }
        },
        "tags": ["media-items"],
        "security": [
          {
            "bearer": []
          }
        ]
      }
    },
    "/api/playlist-items/visibilities": {
      "get": {
        "operationId": "PlaylistItemController_getVisibilities",
        "parameters": [],
        "responses": {
          "200": {
            "description": ""
          }
        },
        "tags": ["playlist-items"]
      }
    },
    "/api/playlist-items": {
      "post": {
        "operationId": "PlaylistItemController_create",
        "parameters": [],
        "requestBody": {
          "required": true,
          "content": {
            "application/json": {
              "schema": {
                "$ref": "#/components/schemas/CreatePlaylistItemDto"
              }
            }
          }
        },
        "responses": {
          "201": {
            "description": "",
            "content": {
              "application/json": {
                "schema": {
                  "$ref": "#/components/schemas/PlaylistItem"
                }
              }
            }
          }
        },
        "tags": ["playlist-items"],
        "security": [
          {
            "bearer": []
          }
        ]
      },
      "get": {
        "operationId": "PlaylistItemController_findAll",
        "parameters": [
          {
            "name": "text",
            "required": false,
            "in": "query",
            "allowEmptyValue": true,
            "schema": {
              "type": "string"
            }
          },
          {
            "name": "tags",
            "required": false,
            "in": "query",
            "explode": true,
            "allowEmptyValue": true,
            "schema": {
              "type": "array",
              "items": {
                "type": "string"
              }
            }
          }
        ],
        "responses": {
          "200": {
            "description": "",
            "content": {
              "application/json": {
                "schema": {
                  "type": "array",
                  "items": {
                    "$ref": "#/components/schemas/PlaylistItemDto"
                  }
                }
              }
            }
          }
        },
        "tags": ["playlist-items"],
        "security": [
          {
            "bearer": []
          }
        ]
      }
    },
    "/api/playlist-items/{playlistItemId}": {
      "put": {
        "operationId": "PlaylistItemController_update",
        "parameters": [
          {
            "name": "playlistItemId",
            "required": true,
            "in": "path",
            "schema": {
              "type": "string"
            }
          }
        ],
        "requestBody": {
          "required": true,
          "content": {
            "application/json": {
              "schema": {
                "$ref": "#/components/schemas/UpdatePlaylistItemDto"
              }
            }
          }
        },
        "responses": {
          "200": {
            "description": "",
            "content": {
              "application/json": {
                "schema": {
                  "$ref": "#/components/schemas/PlaylistItem"
                }
              }
            }
          }
        },
        "tags": ["playlist-items"],
        "security": [
          {
            "bearer": []
          }
        ]
      },
      "delete": {
        "operationId": "PlaylistItemController_remove",
        "parameters": [
          {
            "name": "playlistItemId",
            "required": true,
            "in": "path",
            "schema": {
              "type": "string"
            }
          }
        ],
        "responses": {
          "200": {
            "description": ""
          }
        },
        "tags": ["playlist-items"],
        "security": [
          {
            "bearer": []
          }
        ]
      },
      "get": {
        "operationId": "PlaylistItemController_findOne",
        "parameters": [
          {
            "name": "playlistItemId",
            "required": true,
            "in": "path",
            "schema": {
              "type": "string"
            }
          }
        ],
        "responses": {
          "200": {
            "description": "",
            "content": {
              "application/json": {
                "schema": {
                  "$ref": "#/components/schemas/PlaylistItemDto"
                }
              }
            }
          }
        },
        "tags": ["playlist-items"],
        "security": [
          {
            "bearer": []
          }
        ]
      }
    },
    "/api/playlist-items/{playlistItemId}/share/{userId}": {
      "post": {
        "operationId": "PlaylistItemController_share",
        "parameters": [
          {
            "name": "playlistItemId",
            "required": true,
            "in": "path",
            "schema": {
              "type": "string"
            }
          },
          {
            "name": ":userId",
            "required": true,
            "in": "path",
            "schema": {
              "type": "string"
            }
          },
          {
            "name": "userId",
            "required": true,
            "in": "path",
            "schema": {
              "type": "string"
            }
          }
        ],
        "responses": {
          "201": {
            "description": "",
            "content": {
              "application/json": {
                "schema": {
                  "$ref": "#/components/schemas/ShareItem"
                }
              }
            }
          }
        },
        "tags": ["playlist-items"],
        "security": [
          {
            "bearer": []
          }
        ]
      }
    },
    "/api/playlist-items/popular": {
      "get": {
        "operationId": "PlaylistItemController_findPopular",
        "parameters": [],
        "responses": {
          "200": {
            "description": "",
            "content": {
              "application/json": {
                "schema": {
                  "type": "array",
                  "items": {
                    "$ref": "#/components/schemas/PlaylistItemDto"
                  }
                }
              }
            }
          }
        },
        "tags": ["playlist-items"],
        "security": [
          {
            "bearer": []
          }
        ]
      }
    },
    "/api/playlists/visibilities": {
      "get": {
        "operationId": "PlaylistController_getVisibilities",
        "parameters": [],
        "responses": {
          "200": {
            "description": ""
          }
        },
        "tags": ["playlists"]
      }
    },
    "/api/playlists": {
      "post": {
        "operationId": "PlaylistController_create",
        "parameters": [],
        "requestBody": {
          "required": true,
          "content": {
            "application/json": {
              "schema": {
                "$ref": "#/components/schemas/CreatePlaylistDto"
              }
            }
          }
        },
        "responses": {
          "201": {
            "description": "",
            "content": {
              "application/json": {
                "schema": {
                  "$ref": "#/components/schemas/PlaylistDto"
                }
              }
            }
          }
        },
        "tags": ["playlists"],
        "security": [
          {
            "bearer": []
          }
        ]
      },
      "get": {
        "operationId": "PlaylistController_findAll",
        "parameters": [
          {
            "name": "text",
            "required": false,
            "in": "query",
            "allowEmptyValue": true,
            "schema": {
              "type": "string"
            }
          },
          {
            "name": "tags",
            "required": false,
            "in": "query",
            "explode": true,
            "allowEmptyValue": true,
            "schema": {
              "type": "array",
              "items": {
                "type": "string"
              }
            }
          }
        ],
        "responses": {
          "200": {
            "description": "",
            "content": {
              "application/json": {
                "schema": {
                  "type": "array",
                  "items": {
                    "$ref": "#/components/schemas/PlaylistDto"
                  }
                }
              }
            }
          }
        },
        "tags": ["playlists"],
        "security": [
          {
            "bearer": []
          }
        ]
      }
    },
    "/api/playlists/{playlistId}": {
      "put": {
        "operationId": "PlaylistController_update",
        "parameters": [
          {
            "name": "playlistId",
            "required": true,
            "in": "path",
            "example": "123",
            "schema": {
              "type": "string"
            }
          }
        ],
        "requestBody": {
          "required": true,
          "content": {
            "application/json": {
              "schema": {
                "$ref": "#/components/schemas/UpdatePlaylistDto"
              }
            }
          }
        },
        "responses": {
          "200": {
            "description": "",
            "content": {
              "application/json": {
                "schema": {
                  "$ref": "#/components/schemas/Playlist"
                }
              }
            }
          }
        },
        "tags": ["playlists"],
        "security": [
          {
            "bearer": []
          }
        ]
      },
      "delete": {
        "operationId": "PlaylistController_remove",
        "parameters": [
          {
            "name": "playlistId",
            "required": true,
            "in": "path",
            "example": "123",
            "schema": {
              "type": "string"
            }
          }
        ],
        "responses": {
          "200": {
            "description": ""
          }
        },
        "tags": ["playlists"],
        "security": [
          {
            "bearer": []
          }
        ]
      },
      "get": {
        "operationId": "PlaylistController_findOne",
        "parameters": [
          {
            "name": "playlistId",
            "required": true,
            "in": "path",
            "example": "123",
            "schema": {
              "type": "string"
            }
          }
        ],
        "responses": {
          "200": {
            "description": "",
            "content": {
              "application/json": {
                "schema": {
                  "$ref": "#/components/schemas/PlaylistDto"
                }
              }
            }
          }
        },
        "tags": ["playlists"],
        "security": [
          {
            "bearer": []
          }
        ]
      }
    },
    "/api/playlists/{playlistId}/share/{userId}": {
      "post": {
        "operationId": "PlaylistController_share",
        "parameters": [
          {
            "name": "playlistId",
            "required": true,
            "in": "path",
            "schema": {
              "type": "string"
            }
          },
          {
            "name": "userId",
            "required": true,
            "in": "path",
            "schema": {
              "type": "string"
            }
          }
        ],
        "responses": {
          "201": {
            "description": "",
            "content": {
              "application/json": {
                "schema": {
                  "type": "array",
                  "items": {
                    "$ref": "#/components/schemas/ShareItem"
                  }
                }
              }
            }
          }
        },
        "tags": ["playlists"],
        "security": [
          {
            "bearer": []
          }
        ]
      }
    },
    "/api/search": {
      "get": {
        "operationId": "SearchController_findAll",
        "parameters": [
          {
            "name": "target",
            "required": true,
            "in": "query",
            "schema": {
              "type": "string"
            }
          },
          {
            "name": "text",
            "required": false,
            "in": "query",
            "allowEmptyValue": true,
            "schema": {
              "type": "string"
            }
          },
          {
            "name": "tags",
            "required": false,
            "in": "query",
            "explode": true,
            "allowEmptyValue": true,
            "schema": {
              "type": "array",
              "items": {
                "type": "string"
              }
            }
          }
        ],
        "responses": {
          "200": {
            "description": "",
            "content": {
              "application/json": {
                "schema": {
                  "type": "array",
                  "items": {
                    "$ref": "#/components/schemas/PlaylistDto"
                  }
                }
              }
            }
          }
        },
        "tags": ["search"]
      }
    },
    "/api/search/popular": {
      "get": {
        "operationId": "SearchController_findPopular",
        "parameters": [],
        "responses": {
          "200": {
            "description": "",
            "content": {
              "application/json": {
                "schema": {
                  "type": "array",
                  "items": {
                    "$ref": "#/components/schemas/PlaylistDto"
                  }
                }
              }
            }
          }
        },
        "tags": ["search"]
      }
    }
  },
  "info": {
    "title": "Media Service",
    "description": "Media Service",
    "version": "0.0.1",
    "contact": {}
  },
  "tags": [
    {
      "name": "media-svc",
      "description": ""
    }
  ],
  "servers": [
    {
      "url": "http://localhost:3000",
      "description": "local"
    },
    {
      "url": "https://mediashare-api-staging.herokuapp.com",
      "description": "staging"
    },
    {
      "url": "https://mediashare-api-prod.herokuapp.com",
      "description": "production"
    }
  ],
  "components": {
    "securitySchemes": {
      "bearer": {
        "scheme": "bearer",
        "bearerFormat": "JWT",
        "type": "http"
      }
    },
    "schemas": {
      "CreateMediaItemDto": {
        "type": "object",
        "properties": {
          "key": {
            "type": "string",
            "example": "GpCuqXRAp8X38KvIHccZMrkAWY8nQnbgaTy7aKpCku1fqt0ddctD5Z57NVP3ZVzN8sAzToP3xvjUvXx2gEFKXodN39uHcXpuoZkZPk61svUC1TIElXAAIMeCEw9CS",
            "maxLength": 255,
            "minLength": 0
          },
          "userId": {
            "type": "string",
            "example": "vSriQ809K8EG3vt1aDrxvYfLxd5utjLhwpFy0yJ90OB2Z0MBbjX21jrg7eUnm0Fl8fa5Sxt2fc84E8eoOTme3202wOwfaVO5Dd5Pb4rFPXhpo9HwZanv45e7ELDcQ",
            "maxLength": 255,
            "minLength": 0
          },
          "title": {
            "type": "string",
            "example": "dhFblZgUbP0cI57O1LxQ2D9mb0QJpbV3Ks6UvZz49jCnoRK8XQq1XRvk41lT4RgAGZpLNLoaO4ScGkZyrQJIWey5CPjz7vqyOyAudTt8uuHlpW4qztno1vfFPQSHB",
            "maxLength": 255,
            "minLength": 0
          },
          "summary": {
            "type": "string",
            "example": "0AuMzJTO54mIl9KpTQC4D2JfiP5M6IQVpGXXdCk4XLhMlHFRYwAO2iPlttLWu3lAiv6njHPlqDnddy2Pvy6mfLRCqLHo7BPQMnUdDre3mTmk39RRS6YH3KCyTeeeQBHqL6Ecf3aA1IUDkS1fqYvW1p7EjWUNxz0Sq6BVtjqAc6kd6KRZ1s4x35rDb3zc9zrBloAoj6wzoZnsGBZJugWrO3BRtiNmBAVGCTjGFOhD9YWF0IDrIHOrxqrsa94W8uk2fxratCR8JSOsiq6Gikj2g2m92pQkYcN2qvBKY4be8cBQ"
          },
          "description": {
            "type": "string",
            "example": "HNJ408cSyMoarySpi3OXsSF02FLLPtZPMx9Jiwm5ck4vTBFHmlU25jqgSIFTOxxoDKSef9qJVOseLBLZLSdmG8z4KskshjFsM9Ol2PFQaDDPmpzlrBO7R3g4TjLL8OeKvjzkcKsSOKo2PbEhen2BvoUFepChr2elVZw3n442TbjtGcPdEVt8jmhd9J5d5R9i3YGHNgHo1BqmaBpTtcjU6lXY086CgR72jxI5RtpYRWgv3r9U3MnfkYN1OtWbm6Ug1CMSw2QM6kzWiPquqY03TEu3cBON33YUWyrudRRKjKQk"
          },
          "uri": {
            "type": "string",
            "example": "Hm9klTfBVkKFCWPmc4EUiRngDeyAVPCYqWz4aA8vJUraTanDCXmJ8zslrYTgDtfaQViahtMbFUUVhw0krsrbnPGm4v7EKAHJY3wv4HZkI8lOToQNhJjDeZFzG4jMpq5l82v0qJ5PmVwbhcZxS03suhSwF95A3i8ejfe65XPpdQ1za7MLjTitahQeeDdnnUjq2sTbW0shlcH72KvhlZumKGbKj5eLcDMD9xCWacBiAVpD0u0mUSjo02RJGi1UzHQQV1j4yfLRSr0VlMadnsRVmTF1qikmZ3YVZzuvVk8yLDc4"
          },
          "imageSrc": {
            "type": "string",
            "example": "49HKXsyYrMVWpSzJ6Pr2ZswwAubWWCASc2ozSTwiamCgv1XuBVI11O23o49ciL6zbwno7462uG5jsio6yag6GaERukSFX9cVC9HCs8VVghG3EuBAdosSU4HoBhxtwPDCI6zDUDrY1GgfsyDjr1b492jF1M7eU8McQcikfPgChUYEh9Vsj9Qi3YNTvIj1UlEmdmeKFndpHb9YfKoDqTE7UCyv9uQtNOGLxH8jNKGcW8rmNdzxLTsc60lXS1hr8UqdUDaLxU5EKfA9u1upt73dGg3OJSp7NrBPLtHfu0PRv4Kg"
          },
          "isPlayable": {
            "type": "boolean"
          },
          "visibility": {
            "type": "string",
            "enum": ["private", "shared", "subscription", "public"]
          },
          "eTag": {
            "type": "string",
            "example": "AKttdCuXValFc6dKrWFQr1pgVEaoOyMMGSiSeHWa047BhfBXdNFlDKq6FudRYyfKDqLibvUVpu3RGNZkBOSlRRUGGgmzGpkPaMWqi7nYl7wLnQMD6afspBbZk7JP2",
            "maxLength": 255,
            "minLength": 0
          }
        },
        "required": [
          "key",
          "userId",
          "title",
          "description",
          "uri",
          "visibility"
        ]
      },
      "MediaItem": {
        "type": "object",
        "properties": {}
      },
      "MediaVisibilityType": {
        "type": "string",
        "enum": ["private", "shared", "subscription", "public"]
      },
      "UpdateMediaItemDto": {
        "type": "object",
        "properties": {
          "_id": {
            "type": "string",
            "example": "aIYoYCUSv0PEQHxGl0WTnugNeQ3SC6tysFaZQBpfUALXp4i0aarRnug5DDhvlVRodLQ7FlDoQgYA5uAqVMi9Y0flIbtvcVdSW2fo62eAobCh6QR3l6kpHtHCbFI8H",
            "maxLength": 255,
            "minLength": 0
          },
          "createdAt": {
            "format": "date-time",
            "type": "string",
            "readOnly": true
          },
          "updatedDate": {
            "format": "date-time",
            "type": "string",
            "readOnly": true
          },
          "title": {
            "type": "string",
            "example": "TaD6U3Mq3PtynVwAprqjt8Z6Qw8Xhq6Bx7aG1MzZSNSnsi75ILsMFdXkuJthoaMLecyZpD1FOTdLNzDm01k8ff10ckJEE14ei7byZupLlLMJM7j0u7JLfBSAjtpSL",
            "maxLength": 255,
            "minLength": 0
          },
          "summary": {
            "type": "string",
            "example": "ggToLRFq2jdMxiOYedtrZxMyllEWdybSFMzGVwmr01jvg6yiLBOnIWpIAvXYXPAsOnizuaCNKTexcAg0obCPOHlwynJ2x9dIN0Uu4nmZ1NNA2qcLuBmdY8WMNnSfzN4I5pqDzl8p6scmexb0hRCdIzk7oBcvzePFNHf4jwnjN1fyhDBNptfdSyVIh66O6yYCSK5j078foBAiNVhxSpbBw5ew0ldvG9aBQNRfoDaZ37jW2dzcZmYyw64eXICPO1Uwlq9AhrxG1PM2SuOnAcOhzjHhw5ly56k3p9E5AgNpAA49"
          },
          "description": {
            "type": "string",
            "example": "tkcR9zMKHF2Uool0vvUSZ6RleXcBbuLPNLLSWFvssINfBoGQkw8lYnrdy0rz2RUUneoSOESpOCb9082UmZelDGuUKVZ8mpRfitzaasuqYqzkPnERfbqdVImmTeC91h9Jk2tDfMbeocDxbGLfVhXUzktXNA9eSwFesErT2GDuBNNysoafcwl3aQQSsuUdZ4RiDVO53VEj5rdoWOxQYgvx0lyfkmlw2XcyfUvgVPXvq3IKVrOh00kfOnRlu2kPQmOWANNcWLY5H8TEZNTQEZMsLplnjR9k3Ze3qiccLvmVIT1W"
          },
          "imageSrc": {
            "type": "string",
            "example": "WIu6luFoaM3i2jI9UXJLjSns5C2DlqS8M0zlZdTMDYBvB7q0DUpZR86fTASV2CF0xKgRb9VSG2X0zd4dOWTJEx3Ekba9dvEuAMaGg90RKXPZgKHaNO0dRq1MhFxYuhhmpCKvSPOW0ZujqFw0TmsbFPzG3DvlsM4o4tMBYmnjAme9ht5pC8TTuW4v6giI426iLnj0CGu5Z28EFR1Y2NG5vyKr4HP6fM1hYq8EDunGfiHs9lPGQ4NUxeM2Qq3T0UpnehWVGHUN5poj1izEhAfykwh25x1Cn5EPM8NwTYiAUrzc"
          },
          "visibility": {
            "$ref": "#/components/schemas/MediaVisibilityType"
          },
          "eTag": {
            "type": "string",
            "example": "aXHHo9EMNXwMnyfY0umDTtui0sW2m1A4S1GWXENXKrnvEWoDIONyRdEedTFAdgFTrKAaBS1Kh1xdxsZGYCOm1usxY8v6IakOSucTxJ5ruw5096ViGRFdXmLwoOG8f",
            "maxLength": 255,
            "minLength": 0
          }
        },
        "required": ["_id", "title", "description", "visibility"]
      },
      "ShareItem": {
        "type": "object",
        "properties": {}
      },
      "MediaItemDto": {
        "type": "object",
        "properties": {
          "_id": {
            "type": "string",
            "example": "aIYoYCUSv0PEQHxGl0WTnugNeQ3SC6tysFaZQBpfUALXp4i0aarRnug5DDhvlVRodLQ7FlDoQgYA5uAqVMi9Y0flIbtvcVdSW2fo62eAobCh6QR3l6kpHtHCbFI8H",
            "maxLength": 255,
            "minLength": 0
          },
          "createdAt": {
            "format": "date-time",
            "type": "string",
            "readOnly": true
          },
          "updatedDate": {
            "format": "date-time",
            "type": "string",
            "readOnly": true
          },
          "key": {
            "type": "string",
            "example": "RiNo4IWqQQ4GzrEQSigQNtwbmuCB8ioiV22bDICqvGsFdDh71DWRZLTZFEldK6vkZIg9neF1mfZuIwk6qy4zIEYsaUXv8vNfWJcikWHNKUC0mbxFYLkSqRojg48rh",
            "maxLength": 255,
            "minLength": 0
          },
          "userId": {
            "type": "string",
            "example": "3mj2AeXK3EpU8F20IziSHCaswBDITuH7uyzC7EEgMJCGou0gGEchNbeBKoWei4KkBh9lxjzRoyDTjyaULVfZ5LRatLXFE1W6rECsxZH6SdblVI84K6NMeOA7lYxX5",
            "maxLength": 255,
            "minLength": 0
          },
          "title": {
            "type": "string",
            "example": "22sOSHfTnUccYgbd6yzqchoAobtQEvhxAUwRf1BPYhS0D5g38h5fNG6PPzqfq6oIJzBtlw87rUbQoPnu2aezQq4fkaqbPUtEXi0XUB4iiXWsbxBEZQwkavZ8iZir3",
            "maxLength": 255,
            "minLength": 0
          },
          "summary": {
            "type": "string",
            "example": "p6L44vNAoL6LT7wQVYOSR2g82fzq1pCtML3sLd7nG7gUP8poXhswQGfLdqUV6OF9RLytcZaplHocfBBFaNuSWi5myltdem5O112nWxGCmUEv322fFI7js4XJJSEsb6ebaVaIZz8Kkg3lOz1m3kdv6ftXJBXB9QiJRSBarKXOxLYe6ewNomH9KAZQdpvPhaDk5wOgI9S0cE0kPk7KZvQOQaSDOgbdQrx9VExb7km4dPLIvY5qpLzxAnh92FsyNxWBm2t0gDzr0Bx8YLICylyuq42Y3xdO5SnqAHWHX47TpOMv"
          },
          "description": {
            "type": "string",
            "example": "HjuUUITMqd9rMRhej26v58RwYBVNEyUNrBwuFGmXj4jH21OrKJzQhylW5dvqO4FePjzrNoe4zazTWRno9HXa9htElweCxhx4mkvnW7sezuURe8BIDl3wOWvUpPlZaOtixUzd7D2u2T8t9rljkp1wMpL4EHqf7RgeNjFMfK0K6GjObcXuJbGyLGDI9bMRpTMmLaBv703EHe6IPrdq8mPUAlkWmUvawoFS57YPWZvRnkusjcWLyjHkv1gxeKMMNLYBrYm3zZR9GEtF2cWXNGOxNDmBY1UW2vrBmcZrjao9Wyb6"
          },
          "uri": {
            "type": "string",
            "example": "LNNZwhtviVRGue7exbfXzK0x3WSTzyfT1Bge75MoDlzbakJEAlLWSLTVwJ8OmV9HBscoIby3gaFwgbuY5Rpz4aagSkpG0Q0dK2k9Tw7jHoTFisLusMJk0ZN93qpwg8mD9Wb49Dt6JGjQqDjxr0oekWuW65t8PgMQfnCgG7fj1ThSACWkBWYQKoSGn7vpM7HIGHGqZdI3UdFrKv12RvdToc1FQvHtNampSgaLUwg7fgiFefIsruCdESFqtgmH2Bcc3Uk4Lj4dMzz2VKNH9TfYJbjKdcZrXkPbUkLV6NcsMHJW"
          },
          "imageSrc": {
            "type": "string",
            "example": "AXArM7CFRtKL2hTv0j2F0HNWZ8RAaVjGxFhLOqLm8RL6kf8SdrqbUJqn2wWV3kPC5hXm0XoGzsr1o8DKI70rKGPR79agotCCXLgCI6B3Ig7oMQIenNaUrsCemtrhTpccIAZqYB8FmdNwc2St5pngsT6FDLUmJyYRBz6uTdQ75qKwNN9WPxNL0Ujnkiy9mkFv7UEJzu5oRha6cpEbEMJw1E6Z6iHZcvj6IPZd82P7frP5g4gbLjWJKOCX1V4s4vwIL4JOWgkrx6lF7hVxDjlNw3g8CqQIFzo0Ebb70hXb8Uqo"
          },
          "isPlayable": {
            "type": "boolean"
          },
          "visibility": {
            "type": "string",
            "enum": ["private", "shared", "subscription", "public"]
          },
          "eTag": {
            "type": "string",
            "example": "i7J11v5UYT9zbYlpcQPDYvvlGiANAtZGZoIVC1kPZw99hTZHSLMhT3g3K2xvvKJoxdVmvPppaBaIWcYCjJDHLYbYB2z8I6hauhn0isr1s49KL1xssO7zVuZKNp2wQ",
            "maxLength": 255,
            "minLength": 0
          },
          "shareCount": {
            "type": "number"
          },
          "viewCount": {
            "type": "number"
          },
          "likesCount": {
            "type": "number"
          }
        },
        "required": [
          "_id",
          "key",
          "userId",
          "title",
          "description",
          "uri",
          "visibility",
          "shareCount",
          "viewCount",
          "likesCount"
        ]
      },
      "CreatePlaylistItemDto": {
        "type": "object",
        "properties": {
          "playlistId": {
            "type": "string",
            "example": "1jX01z5Va7h3iAzXETMPl5t3CxD8hPnMdVmSXC9kzKK1ouC7Yu8LIn5bjtjBVmTYmMYzkFjkPK2UqbffVnKy5XhTbYWl1Ju1JMwunXE7nkJRmEvJ1I38maUkh1rcY",
            "maxLength": 255,
            "minLength": 0
          },
          "mediaId": {
            "type": "string",
            "example": "zEompqfW5t8ePF5TG8rBhlSBV07AAOY8wxq3McWgebRXI6zUyncGUTPItyt3zW6SgBPvuvGJ3hKoi7u2bhchxVUirWUpt1c3xp1VQJ7oRjOTV9suxdKFxOQqsi6ws",
            "maxLength": 255,
            "minLength": 0
          },
          "userId": {
            "type": "string",
            "example": "9YexUshUGtqcn7BPFUrsvpoC3GmDm97Ws7H7ZDSjHHg0OMVUySzLhvdIzTW1yr6VNosaoiUncrWB4zIS0l9UiecoiWoc7CnfF3xDEyzPlXg0FX57rBeokgdI2hfdC",
            "maxLength": 255,
            "minLength": 0
          },
          "createdBy": {
            "type": "string",
            "example": "cBYVrEAqnTkLmEdgfEiZ4BpspTEebfOEc8zOEB9Qp4K8dcFgr1zIXVqsekj7ZaBj0C5Ddp364sPyfkTGZoSznqIHfQ0fQq4C3Qr1Tw3JaCcnuzlrCLMPONwQyEoMG",
            "maxLength": 255,
            "minLength": 0
          },
          "title": {
            "type": "string",
            "example": "ttN1FZq9jvgNmDtUyx8neoBzbriTY7bDJzgEL3wkxJOrG1iPPnuUKn5DHBXYGPNPSOdCh68KpxvbrdVN6BxsdlcM48v9bdqkF0Vw1Q7hLqUzAzGBqR18vneFMSelZ",
            "maxLength": 255,
            "minLength": 0
          },
          "summary": {
            "type": "string",
            "example": "qFXqIR6tQCnZxedBWiwRRsKPYnxddoWyLvYnZnBLeUzlzQE3gQEugfepQuYY4OksGlkElaP4hhCGwaIy0XrNUJ2BaQgGkTgeoe33PtP2a7XXwoVFUaFFwy3xGkxq4WmsuHTOIXIVL1Ho20TjeiHlriBlVcXvr9K0pxgQ8S9XQ3JVFxTAF6nIlOLQVkvDyfCuTYq7LmH4AlBjqsh3dXOlCEhWvN2rn6P6c87V9RrCDesfY782Wjpiq0d7nzxEqlFO9iZbere8tyw9FgK3pWoZ3bIUh9KpXTfb7tVHLQ43Vf7N"
          },
          "description": {
            "type": "string",
            "example": "b7C9eW0IKvEZhtEneNlLtzSQca5R2zdaFIPLUZvOSJRHRnpnknapi7BSnGXqSI8HeOWniv9i0aKNAjjEDh1QJOzoPDZtcc7yBxdY7QyHLXWE9NlMkZUQHyZ9XNYJbdxf6uC5nVIxhbW9DzpI3orH1CffgbD7zZoX23uPm6tySrNWtZzV5kTxfNihThfWNhL3lXihLjDSWkT3Lmji1Kv2Yso625ng7hx81VqLzCge2HjYIAeibfBbuE7wFgniyg2tZVIT7oEM7Z9CtcaMY5hnGH5JxlCuiLK2yeeTk4N9HFaT"
          },
          "uri": {
            "type": "string",
            "example": "jOLMVjAYd9iU9hTGnjLRMpwc5VlGWs2IDABL3V5dYvfW85dxegeWGN1pNFBxJlUTywfnh0YSItmmimFyeTona3kAE098uL4TtJqqE3jQR8Ij45zm4kzlHe06aIFJuMBCIlg4vquReNlIeXjmnGVh7ulsLmcuFIikveGL4jIpboZszwDWeKT3bDJbw6C8vzU7FDuSunMbc8yAP1t2tqq5f6U5ns45Y8oOQWF96ERIrMFlufrfaCrrMmfEpAuO149SzFErDw3jF1QFBNqisIuj1Ywj8U3Q2vWm8H9g17aHxN8q"
          },
          "imageSrc": {
            "type": "string",
            "example": "4ZqT0ZIaOoZ6qfDwX2cshiwetBBe5XxuPwX4saQsTKilhCONrfEXOGsbWxoY94CzFudpCecCO2gOcS7uxIRCqmSMosFzhEHHKdQKas69gbIWYcxLb0HPpIuUmvSIV1YduHlZzbYM5hBgOHQgNe3dCKLbzmOjpPkVl1YOGPszfCZF6OQJiO2R3qfEjYAFTrkFibfUY4jW0pMDBuJoSh6TPcwhiwET1vracwmCJ2URG8DY2rZDtweZSFSp3nnjkhMiArDmcVkPGEnhvCDIFwkum8BmhjXDMzm24t1CnA7HO81F"
          },
          "sortIndex": {
            "type": "number"
          },
          "isPlayable": {
            "type": "boolean"
          },
          "visibility": {
            "$ref": "#/components/schemas/MediaVisibilityType"
          }
        },
        "required": [
          "playlistId",
          "mediaId",
          "userId",
          "createdBy",
          "title",
          "description",
          "uri",
          "visibility"
        ]
      },
      "PlaylistItem": {
        "type": "object",
        "properties": {}
      },
      "UpdatePlaylistItemDto": {
        "type": "object",
        "properties": {
          "_id": {
            "type": "string",
            "example": "aIYoYCUSv0PEQHxGl0WTnugNeQ3SC6tysFaZQBpfUALXp4i0aarRnug5DDhvlVRodLQ7FlDoQgYA5uAqVMi9Y0flIbtvcVdSW2fo62eAobCh6QR3l6kpHtHCbFI8H",
            "maxLength": 255,
            "minLength": 0
          },
          "createdAt": {
            "format": "date-time",
            "type": "string",
            "readOnly": true
          },
          "updatedDate": {
            "format": "date-time",
            "type": "string",
            "readOnly": true
          },
          "playlistId": {
            "type": "string",
            "example": "g5PmJ0DJVrq8c8IFleMogZ3suhm5MvMfdRsVqbe5Dmsy0f2XgdUSVUz9YKisBjTQpPHURKaB8425e14X8mXiq9JkCMH8a8iolJMShEUThLIcvgQgrORdWtn0rjBmy",
            "maxLength": 255,
            "minLength": 0
          },
          "mediaId": {
            "type": "string",
            "example": "uILuZEyQbPJfpCjyx80n4hUZ3CqvS0MJw5oSEHGSXETn0BCuhhOJnulTYtunshuUpqR3aRmJA1AmjhwCbxhTJQBHwpNNItCClIaGsatgk396Wr4P5Nd4rdu67yIvs",
            "maxLength": 255,
            "minLength": 0
          },
          "userId": {
            "type": "string",
            "example": "LHSk2SOOghUzvLPG8FPaif6wLi9rPhSuPBoY1OVuoyYN6AoyXnwRSPYH7c4BDv5OG7ZAFVwGUVeS8fgqHRlSzidSTOV5zzxmNkMayWtxsxKeQFEzPbXARjUQ7W78D",
            "maxLength": 255,
            "minLength": 0
          },
          "createdBy": {
            "type": "string",
            "example": "0szurrFQ30mKLPTbFg4KJc3v748JblNor4CRnNXcspBspWZCXXuBnTemXBf8aZ280MDEk1PYsAQsGIhpJjNI5z7xA7h4RJ2jxwHYDaTxhj4YAr00R4kt8TQh2QO37",
            "maxLength": 255,
            "minLength": 0
          },
          "title": {
            "type": "string",
            "example": "9Ku42j4NXgAd02JLoTIumDUBp3xcRgzNOlYwN96UfRcN38bkP6terNgqmJlFVKupNl9q1qN8uG9RjGl8vXeOqlcOHHQczP332PA5ViXXFm0lzMtk4rWiH0M80QrlO",
            "maxLength": 255,
            "minLength": 0
          },
          "summary": {
            "type": "string",
            "example": "Whmifr1VA8qHog3IQ4le8XQt4MAlwlUSCKwsTdS3TzQITABaWQaqLKJdkuFiqazso0zrRFiFHTGV0BiGnQHQo6m5m8LhJ9PoTjnGsXX6Fceie7zdHaGeN9Tv6OmsxRVoHY7YDpQQEnt2BYvYvHoJfLTv9cLg2hrA6wy5tLgGns16MqmjGmuy8OlaHzBlfgPV2kXbq8WjCJFKH4ApAuO8YdHtp2Qq71eaqVcAkgAu9lz2CbbSB4NhTLgCUaBnLZeBOzbwJ0SraWDfJHOndADMNklmuwwDD1gAifNnfoel5cwb"
          },
          "description": {
            "type": "string",
            "example": "Wumhta2pcgkztGBOud2Julr51tAqaPHHtQiQl7raq0ocH4VXNTbGTK2NmhjKgnRmJK6yTGh8vHtOD0Bjzwg9CSD6gX85sG2t2mvKMdOtunY10jecHWoEjO6GP8L3toXonFVtuCdgwPGCbJNlVo3XanQhJ7m9cM5EQgI2x92ltSZSZ3se5fXxAVNPslRzgkLSOk6deuWS4L08EDVvh4mbIkoOoHKvLZdzLrsHnRkPmnnQXVEDtINtAi8wh0eju1opFRP5h1AvE237sUzIrxUMC5beBTEW4XRAsz50luDfRRoT"
          },
          "uri": {
            "type": "string",
            "example": "Jp8Y8FiA76EHOksQOytREHcLlwBbIeGey254wjWmWK3T6epFcxssZLVKQPxH0ulrhR0VBnEuBrnwkcK4bOmShsXbXxNdZ61svAmAT9DTW5u9o3OfFSFzexfnB0xOTe7P3oxiXHqEbdZG2pkbhex5BFf2eldlYqSMpXji8tFNDf329Eee1Wcj8AJXFnOCPaHZIJ5plw4J5LglQEUct4eVTs9W41Yy7Bajd3pB7ekUESb8UD1SDbc2K8QzPY9ZCRrLaK86Mf5EbKIDM4fvSLYNuoMgT726eJUuoNwDfvSS45sg"
          },
          "imageSrc": {
            "type": "string",
            "example": "mTRqw7Jjks99RCADGlkjBrjk4UxNHJQJdGRqneTNXHtJmopYCdO05NTHUjgnnH9r6TaWFGsRnc0FbDiSDliFRPUrncfO2kqZJGFl7Jloq6OReTdy19Awd5vHJP1xKPYl8wfUI8AeEtkIGoGOcS8l0kSalpka36JNiyIEOsqE9Y1AR5Y3iivZZ6GoWsY9yncJTKQgNnX0ZZ3mOkd6DzT39kjCLb8dTAwVbGs1TnrSKgxh9HWJCA7SQpaaU3yjISbOT8vLkCp7Q1P0X3QCC3Qchp3FXZ9ZsiFCADc4hLxWEy3Q"
          },
          "sortIndex": {
            "type": "number"
          },
          "isPlayable": {
            "type": "boolean"
          },
          "visibility": {
            "$ref": "#/components/schemas/MediaVisibilityType"
          }
        },
        "required": [
          "_id",
          "playlistId",
          "mediaId",
          "userId",
          "createdBy",
          "title",
          "description",
          "uri"
        ]
      },
      "PlaylistItemDto": {
        "type": "object",
        "properties": {
          "_id": {
            "type": "string",
            "example": "aIYoYCUSv0PEQHxGl0WTnugNeQ3SC6tysFaZQBpfUALXp4i0aarRnug5DDhvlVRodLQ7FlDoQgYA5uAqVMi9Y0flIbtvcVdSW2fo62eAobCh6QR3l6kpHtHCbFI8H",
            "maxLength": 255,
            "minLength": 0
          },
          "createdAt": {
            "format": "date-time",
            "type": "string",
            "readOnly": true
          },
          "updatedDate": {
            "format": "date-time",
            "type": "string",
            "readOnly": true
          },
          "playlistId": {
            "type": "string",
            "example": "YdQtKUNOPV5wQPqPrdCqCHKX3frT8cAMeQp5LEyFasMPuX53qaQ79BOSj34EgI7GspsU056nZ4wBomGtkPsw2chP9cUw2S0cRgtla8Jm85A8zYKKvULHvAYGt6NnX",
            "maxLength": 255,
            "minLength": 0
          },
          "mediaId": {
            "type": "string",
            "example": "Vtq5Pct8sn4dR1EOGKOYdlOYKS8zvKRHcTPBXcfs0g8A2Lv2rr6g4lcATqMRgytMTfzqcV6cBi3xAwkMSh7BzQI8b7ZmouHz5EP3oBT94Ymyz94Qous91uwKy6zvt",
            "maxLength": 255,
            "minLength": 0
          },
          "userId": {
            "type": "string",
            "example": "wVx4Fp8BZqD394nlZwWHmjYk2ieg0jn3c1PljGGKY4hOGSbeS78jZbgET0udBJpOhewBxIaRIYFoZO9TVIWTXLNYOu5dClpQjEwTo4oyHQFg91RoEA5vsQxkYK1Kf",
            "maxLength": 255,
            "minLength": 0
          },
          "createdBy": {
            "type": "string",
            "example": "bhOB2AETI4mH69i5fsIxG4dV9ZkiB47GXPG7tl6pqiYcnm889GO9k30jnkoDNmRjsK5HSnaNI2UM7oSHj0acCtuJNcwISCKMhCPjrY0i0ooDsvuPLlGSWj7mXMRBJ",
            "maxLength": 255,
            "minLength": 0
          },
          "title": {
            "type": "string",
            "example": "HaCaIbwbLPpyxW5r3Y7TSygKlPXgKrBTGgQyAAhVarof6tAJNJalfLzxman6PWscFfC2B7x3WUiL5tTxzCwBorzlwLJNmnUpX3sKXsuREwlHtGnqTVinh1tPqUFuz",
            "maxLength": 255,
            "minLength": 0
          },
          "summary": {
            "type": "string",
            "example": "9vBK5UdfWi7HKrbrivqWtTzzBOkVQXKBt8rSnpjH6SjF9Uhb028TVhDHcYs9ZQkM3IMnxQjE4MfZfIf7tT7hsDkYEXvoGmvVKVeXbM8IsR8yPTMwoGXdwdMVkrI3EfIMxaB846if0BBx3xmyRIPnNVfWiLsEvvGL55GZyZMA61N8pOoYDAGyQ8UVzwpHhet8Wwq5pOOYEpg72UJEFLh14lGS50uXtby0jQPMxBqc7s2gpri60ogrmo2gg7HtpsYBI8RwQbWrccEVotVTVObqVmbDnmsq9adJulL7LCgwmh5a"
          },
          "description": {
            "type": "string",
            "example": "THS7oNO6EFsVAEowEa60yO6jVKIJbkxPj41ZLYiEtDx0FVsEUXZhUMxKivJYwucaKrWNGXdZWN2QKsw0USIaobR3Hdd50pomkip7AReIxXqjBjvrIhEiAQoGsEgqBdQ0pRRH7grKM99HL0qflh5fOwlrq6Go8Jm93qAfzjV7y2btaVL7e9bitpPkVbeOSqdPgKcDS7LpPFnTPgwLYYWZ42osvINYNcY8NPKX5FCzyyVK0KYGNNqu9NQZLdbrnQSqynqoeMrqsARh00LdPcZgTvqGvSWkL6vgAVE8AdihqCE7"
          },
          "uri": {
            "type": "string",
            "example": "OprB6kyzzEODhudDTwdnidGHHix2KEDHjgTqW4COPDPS8fAoYt2PvTMe1ZNs1TrhEEPSYI7YCj5PDatHHJJa7aniwDuVA0G8FORSUnL2Uyln3Ct8Yl8P820tRbHdYVv2IBV0M4ayP5PsAof8eBPHIgg1QywZbTaa77U5pmoCuGj5bDnQ5nQAutELBzUc5j1Vw08RjngzebafNETfEtFggpyiKwYqzvMZBfeiB7kw5ixBYwQiEr3rQYmZ7F3xJ6Hq6uSmBoTlHmv7PpNGG4nVCpnB9u314WT03iGFE6zK5ZEE"
          },
          "imageSrc": {
            "type": "string",
            "example": "uDJklWlKeoVKuTSSPANNxITOgmGwWUirX5Vo24YyGbV6qERPEO0vmtSbFeTFS1LMkm8FDrwwBYQyK0MwjdFepupyjX0C16vU1XzvmnuPc4EJw3vHXXb9RC5X604YOUTxY8iBtbTBSHYt0fpdLiLdeP7eNPCijEuYODgx3Zm3WTWUDhBNEBtLOIClybeKyZavmBuO18CTLQEAr1EQDMTQjLh4c7hwojeMY2NlJJToClAibAOgLqzyocS5Pfr138CHx9DNpeDVMr4j6m9C9X8nFaMwm1cucuTm8dU8eY3J2iH5"
          },
          "sortIndex": {
            "type": "number"
          },
          "isPlayable": {
            "type": "boolean"
          },
          "visibility": {
            "$ref": "#/components/schemas/MediaVisibilityType"
          },
          "shareCount": {
            "type": "number"
          },
          "viewCount": {
            "type": "number"
          },
          "likesCount": {
            "type": "number"
          }
        },
        "required": [
          "_id",
          "playlistId",
          "mediaId",
          "userId",
          "createdBy",
          "title",
          "description",
          "uri",
          "visibility",
          "shareCount",
          "viewCount",
          "likesCount"
        ]
      },
      "PlaylistVisibilityType": {
        "type": "string",
        "enum": ["private", "shared", "subscription", "public"]
      },
      "CreatePlaylistDto": {
        "type": "object",
        "properties": {
          "cloneOf": {
            "type": "string",
            "example": "656d708f98937b4b9783b524",
            "readOnly": false
          },
          "userId": {
            "type": "string",
            "example": "cGSrvQkhLhqBOKmbumn9KOtULjA2c7KMxwgnI9nl62ZuCuyIlx4R58DdowMgTP1HCWZavlPbNHslZdtJgcobmat5FuPhnUKyjqY59XQuIV7Y548fKPtRdwNmn6h06",
            "maxLength": 255,
            "minLength": 0
          },
          "title": {
            "type": "string",
            "example": "qg7zAXVyEJPMweLHusks7rjimSYmGxuT5PWIplhnC58xfzmYtEMbJes8aj9GcYK6oNnh3zkwB6UxHWBThDVM5CznXti9sfCc0I7EjOyjVvY5LNC684Mz0B4V7Mtk0",
            "maxLength": 255,
            "minLength": 0
          },
          "summary": {
            "type": "string",
            "example": "vty0jpgAyaeTrcqKuCC3e9NyNMUNoaYgEXEPQTaDC6HSpYXDdRE7b19nQesgGJVqlfRuyiij03H1F8zfXRBoLZnqnCOVM6l1hjzPNMFgYCYM19730Vu8h72WpxZyarGhkj4CnpiU5CxboyYXVtsR3A0sQvxcAUfExl5iFxFres5MkAqz5mCUBWoIpkAhhP9rqWn7x7v81vtJ3krodaHLZ7OYoCr01zPdsyXsl2iVIsTkicJ08az8UAiAw3b7zUzJnZ9vaPVPAUZqHMc2ejkxYU6kMlHTna512imBfVUvnrGS"
          },
          "description": {
            "type": "string",
            "example": "8VHkYY65UdfjgIP2cKsdkgpRBL6l2Esw3xUNc60ufmW3e7uNfJvdyOXBNyrBbECu5xeJKg0wbQ4cx43s3KBTbdXJy4EHSbE4F2s6kBHrn20617GjzKsVeuNszB2bF7Hyoypr4PgoZHXBf1to8EJbRmCEolq705uWrl7lQdvJ5MzXSUOO3SGDL04BtoWYVXM8So40aZIxwfafQZloJ7WCQjfPru2jpfCrwam7dibqQ7od0idOwt5oOgXgFx5q6F5DX3wNjdGAwL8qCQbuk5NidLDpY1XpCrel9O5NPZDP4jrZ"
          },
          "imageSrc": {
            "type": "string",
            "example": "6YxDjdwqtN59O2iz3zWwuoVMEPt2YGbyrgJwZ7TbvwWHWYi3PrGspGcmBctqGq7pHq15POwx1s4aSw3FMph8JVxAxDrvEqhlwtKUpcnii1uyOSEK3FbS8JisW4Y2mrxWx32SgBlEaaDW9JGXipUldJSQjk2TQx2epdkRZzr7RoyennTKB09pVh4CUBgPCFUTsxRkN4PqqdvEHWyYrWOmMnv0kwWXGWDeQUYcrfjrke9JTVIXaQbnEkchBegA618lfYQDpHCQTavaN6IRgYpcEJKVGAPDp1YIWlVgMuWnZrHl"
          },
          "mediaIds": {
            "writeOnly": true,
            "type": "array",
            "items": {
              "type": "string"
            }
          },
          "visibility": {
            "$ref": "#/components/schemas/PlaylistVisibilityType"
          }
        },
        "required": ["userId", "title", "description", "mediaIds", "visibility"]
      },
      "PlaylistDto": {
        "type": "object",
        "properties": {
          "_id": {
            "type": "string",
            "example": "aIYoYCUSv0PEQHxGl0WTnugNeQ3SC6tysFaZQBpfUALXp4i0aarRnug5DDhvlVRodLQ7FlDoQgYA5uAqVMi9Y0flIbtvcVdSW2fo62eAobCh6QR3l6kpHtHCbFI8H",
            "maxLength": 255,
            "minLength": 0
          },
          "createdAt": {
            "format": "date-time",
            "type": "string",
            "readOnly": true
          },
          "updatedDate": {
            "format": "date-time",
            "type": "string",
            "readOnly": true
          },
          "cloneOf": {
            "type": "string",
            "example": "656d708f98937b4b9783b524",
            "readOnly": false
          },
          "title": {
            "type": "string",
            "example": "js5ofkDpcMpXmnUpi2ykhSekhcN4yAb5zISVbyvciq5XEu1IAyusewNZwt14MuR1bPWB2yVnwzxbonsSoDRGj83MFiXHJZ059hBwOdMK5tW9Dpg1HbDEbfvNtP1BL",
            "maxLength": 255,
            "minLength": 0
          },
          "description": {
            "type": "string",
            "example": "ZetGyPyS2MeUGWjUYEOPS2HIIG7iOqfUOS5c9wcq5qvNz4MoGSYJuV3qKK3yRHMZtxdpbE4leO3wd4dijYaqW5J13oOadFlg4rKz1B0XHwZ53Omj4jIk4p8T8W0VHvZt85Gm6YAf0nqflEw0qDSowVw8dOJuoiV9JIuol1dK1M5D86DAQYSP8G9teAqwsaML8XjTiZh2hWgubc5fSltoL5KNVqLvICxBUP0kmAqTgbBHvelgelRCJTnvfqIBXAEzVjDwOTvnXDFMLQzzfpxFlp5mnadmmazyfywO563a2s0V"
          },
          "imageSrc": {
            "type": "string",
            "example": "nU3PVrXs8TOm5QT1z4AZdjND3zDE1T18L3EOj9OQKNWierZayhdgqfaaJBGfzxDeZNC6NOwelB77WlHNFrickDMSpD7mY8xL3KYXrWetlxJALjqQFkR0fcRoEbs9zyzZbEecx3IuqwHmITItsVdNLaidE0WWCZSdjsBwsgkF7CFaJztWQOFiRoK7Q7uNLUkZmpub07MGVR6F3tp63FuW8RGWEs3lCZ2QokIJYwWx8MPr9JWH5tg5XSfueQ4lrElWAWm7kJJTZWqkeiAwfS04ztKJZk4vSfxht4qD7WUG0Ebu"
          },
          "visibility": {
            "$ref": "#/components/schemas/PlaylistVisibilityType"
          },
          "mediaItems": {
            "type": "array",
            "items": {
              "$ref": "#/components/schemas/MediaItemDto"
            }
          },
          "playlistItems": {
            "type": "array",
            "items": {
              "$ref": "#/components/schemas/PlaylistItemDto"
            }
          },
          "shareCount": {
            "type": "number"
          },
          "viewCount": {
            "type": "number"
          },
          "likesCount": {
            "type": "number"
          }
        },
        "required": [
          "_id",
          "title",
          "description",
          "imageSrc",
          "visibility",
          "mediaItems",
          "playlistItems",
          "shareCount",
          "viewCount",
          "likesCount"
        ]
      },
      "UpdatePlaylistDto": {
        "type": "object",
        "properties": {
          "_id": {
            "type": "string",
            "example": "aIYoYCUSv0PEQHxGl0WTnugNeQ3SC6tysFaZQBpfUALXp4i0aarRnug5DDhvlVRodLQ7FlDoQgYA5uAqVMi9Y0flIbtvcVdSW2fo62eAobCh6QR3l6kpHtHCbFI8H",
            "maxLength": 255,
            "minLength": 0
          },
          "createdAt": {
            "format": "date-time",
            "type": "string",
            "readOnly": true
          },
          "updatedDate": {
            "format": "date-time",
            "type": "string",
            "readOnly": true
          },
          "cloneOf": {
            "type": "string",
            "example": "656d708f98937b4b9783b524",
            "readOnly": false
          },
          "title": {
            "type": "string",
            "example": "EvIkO4HbgWm3esWoaZFbeRH8gCHdkkOE92PSOp0JAqwIxrRQniXk9X942EYSVtQN6kEBYfjUDz50AkncFb7aN3pfWD5LQbDDvqJr0da4orzEhlwxrTPRtNDZZM0GL",
            "maxLength": 255,
            "minLength": 0
          },
          "description": {
            "type": "string",
            "example": "0x5EW9kBe9YtTNUX1eUvEaXvrxv0h3ar4kE8lvIJ9iTGRsSboXfTYOn233r2elEJ7LcskZzQ1igit7Wpcq9oVI5RB9qYdY9Pta5LnVCqHgKFNDp4HREE6kzl6KXrJK3UXBjkAMMKqNM7rARM7EhQPPCVOG7G3vVJ7BaAkEwADQDm6DQdoWYyrhMrdP0fzjGEBmPuA6DQ8DZ5mYLUAPrL8tkfqeG0e9DBZ0ZOi2kcgNXwD2ufz6JcXPlUFiYAZh0HPp2FEA3jiKMJbJWtXqjLlYlB7jTMnTUbwN1w5fWW6F6h"
          },
          "imageSrc": {
            "type": "string",
            "example": "cWNra89rBHHUGmUF0zADxf3fGzVAVWWzb8ZsJXOAW3FGnpMfDBpE3sP9003E09YCmtRE1hAe5f9KPcdsyyLNXAYVg0AHpXqXjJTec01qrsdAEbe5txbtqeZDjMibGzGJ7UWQEjyxceEPv9AuZDesREOniBz6xabpJgcOJRjkpzQKwlx41zVc7qLvGf0lJ0r3nFw9kGhSns0LXsITRsFmwaChPwlQncSnByUfm32SFCqCDT2wiAzVXaHkU81X9Do1JIznfESdq8eHq0FkcgCklju04iyNax2gSRbEanxq89U2"
          },
          "visibility": {
            "$ref": "#/components/schemas/PlaylistVisibilityType"
          },
          "mediaIds": {
            "type": "array",
            "items": {
              "type": "string"
            }
          },
          "playlistItems": {
            "type": "array",
            "items": {
              "$ref": "#/components/schemas/PlaylistItemDto"
            }
          }
        },
        "required": [
          "_id",
          "title",
          "description",
          "imageSrc",
          "visibility",
          "mediaIds",
          "playlistItems"
        ]
      },
      "Playlist": {
        "type": "object",
        "properties": {}
      }
    }
  }
}
